{
  "todos": [
    {
      "id": "986f",
      "title": "asdb",
      "date": "2024-03-14"
    },
    {
      "id": "f486",
      "title": "abc",
      "date": "2024-03-12"
    },
    {
      "id": "e0ed",
      "title": "asd",
      "date": "2024-03-14"
    },
    {
      "id": "ecea",
      "title": "sandhya",
      "date": "2024-03-09"
    },
    {
      "id": "e5a9",
      "title": "abc",
      "date": "2024-03-15"
    },
    {
      "id": "7693",
      "title": "abc",
      "date": "2024-03-09"
    },
    {
      "id": "d753",
      "title": "abc",
      "date": "2024-03-16"
    },
    {
      "id": "f15e",
      "title": "rohan",
      "date": "2024-03-12"
    },
    {
      "id": "fd78b7a5-7fae-430c-8038-2e2ca2f03d6a",
      "title": "abc",
      "date": "2024-03-07"
    },
    {
      "id": "2684a074-ae55-444c-9add-db73226de1d8",
      "title": "abc",
      "date": "2024-03-07"
    },
    {
      "id": "f039d3bb-02b5-4adf-921c-5289ed269929",
      "title": "abc",
      "date": "2024-03-14"
    }
  ]
}